kubelib
