Metadata-Version: 1.0
Name: kubelib
Version: 0.3.0
Summary: Utility wrapper around Kubectl
Home-page: https://safaribooks.com
Author: Jason Kane
Author-email: jkane@safaribooksonline.com
License: Copyright (c) 2016, Safari
